{"cameraMode":{"drawMode":0,"name":"Shaded","section":"Shading Mode"},"sceneLighting":false,"audioPlay":false,"sceneViewState":{"showFog":true,"showMaterialUpdate":false,"showSkybox":false,"showFlares":true,"showImageEffects":true,"showParticleSystems":true,"showVisualEffectGraphs":true,"m_FxEnabled":true},"in2DMode":false,"pivot":{"x":10.267647743225098,"y":9.8389310836792,"z":-6.473260879516602},"rotation":{"x":-0.008921929635107518,"y":0.7574403882026672,"z":-0.010128740221261979,"w":-0.6528372168540955},"size":3.4218714237213136,"orthographic":false}